README.md
setup.py
wordpress_cd_s3/__init__.py
wordpress_cd_s3/s3.py
wordpress_cd_s3.egg-info/PKG-INFO
wordpress_cd_s3.egg-info/SOURCES.txt
wordpress_cd_s3.egg-info/dependency_links.txt
wordpress_cd_s3.egg-info/requires.txt
wordpress_cd_s3.egg-info/top_level.txt