Metadata-Version: 1.0
Name: wordpress-cd-s3
Version: 0.1.1
Summary: Rancher driver to deploy WP artifacts to S3 buckets.
Home-page: https://github.com/rossigee/wordpress-cd-s3
Author: Ross Golder
Author-email: ross@golder.org
License: UNKNOWN
Platform: UNKNOWN
